{"base_browser_cache.md":"04231de6","base_browser_engine.md":"44a73fb1","base_browser_api.md":"44e77492","base_browser_browser.md":"3acff9dc","base_browser_cross.md":"abf8c8bd","base_browser_eventloop.md":"25bc1553","base_coding_tool.md":"c2110b26","base_browser_performance.md":"0a1608a9","base_coding_array.md":"83cdab3a","base_css_fragment.md":"4c514e58","base_es6_esmodule.md":"86c94af8","base_es6_arrowfn.md":"beccc5d2","base_coding_simulate.md":"7ae37a85","base_es6_deconstruction.md":"ab89c6bf","base_javascript_this.md":"ece74c75","base_javascript_prototype.md":"144d1352","base_css_base.md":"8ad67654","base_secure_attack.md":"467ede17","base_structure_complexity.md":"1455b1d1","base_structure_queue.md":"5ffb766c","base_javascript_function.md":"f8c7c2e4","base_structure_stack.md":"277d1df8","base_typescript_assertion.md":"9811e2df","base_typescript_class.md":"d1b8d6d9","base_typescript_built-in.md":"91628496","base_typescript_compatibility.md":"75888f6c","base_typescript_decorator.md":"116de9b8","base_typescript_tool.md":"79946ca5","base_typescript_ts.md":"bac60c7e","base_typescript_module.md":"1d533a7c","capital_construct_rspack_base.md":"eb3b0227","base_typescript_tsconfig.md":"08f8e9ca","capital_construct_vite_base.md":"9a4efbe6","capital_construct_webpack_other.md":"eb92f7ee","capital_construct_webpack_sourcemap.md":"2fdef30f","capital_construct_webpack_plugin.md":"20acf43f","capital_construct_webpack_loader.md":"dcc521c9","capital_construct_webpack_webpack5.md":"5f115e30","base_typescript_type.md":"fe516ad2","base_es6_async.md":"dd7eb20c","capital_engineering_monorepo.md":"78b7e99a","capital_construct_webpack_base.md":"f2765662","capital_construct_webpack_optimize.md":"e51c16fb","base_network_httpstatus.md":"0185d708","capital_deploy_docker_command.md":"2db45d48","base_network_restfulapi.md":"da48afbf","capital_deploy_release.md":"096de81b","base_es6_promise_promisemethod.md":"c2c90e1b","base_javascript_extends.md":"2bfaf19b","frame_electron_apply.md":"97bcaced","frame_next_rendermode.md":"3caa54b2","capital_plugins_eslint.md":"91a8495b","base_structure_heap.md":"768b87d4","frame_electron_introduce.md":"7026263c","frame_electron_update.md":"d2a4cf18","base_es6_template.md":"64d59664","frame_electron_process.md":"e4c1f457","base_structure_search.md":"95d9b143","base_javascript_datatype.md":"84faa14c","frame_react_base_hooks.md":"26cb202c","frame_react_tool_zustand.md":"2915037e","index.md":"8e760128","nav.md":"99bb1ab4","node_base_base.md":"7100c1ac","base_typescript_generic.md":"adef28c7","node_base_buffer.md":"6318f98e","node_base_cookie.md":"a1c3661e","base_javascript_context.md":"62b45158","base_typescript_function.md":"f6291202","base_structure_tree.md":"4cc0f4e8","base_network_tcp.md":"035fbdaf","frame_react-native_init.md":"256029e8","rsource_react_file.md":"7aeea1e6","node_base_jwt.md":"73c4b86c","base_html_method.md":"77dca41b","rsource_react_completework.md":"47da8879","base_html_base.md":"c85eed93","rsource_react_commitroot.md":"90588bf4","node_base_eventloop.md":"50bd44c3","base_network_httpagreement.md":"ca00275e","rsource_react_create_fiberroot.md":"43b71ccf","base_javascript_closure.md":"32491b95","capital_deploy_docker_base.md":"778697e3","base_es6_set_map.md":"80aac04e","rsource_react_introduce.md":"246324e3","capital_plugins_chrome.md":"3c44ca1b","node_npm_yarn.md":"dd068701","node_nest_ioc.md":"4ce99976","node_npm_source.md":"6329d768","frame_react-native_getui.md":"6f3dedbc","rsource_newfeature.md":"96e2d36a","node_base_event.md":"bc9a8a47","node_nest_aop.md":"685135ee","base_structure_sort.md":"fa2dda5b","base_network_websocket.md":"eb58a1d0","base_es6_class.md":"fbba845e","frame_react_application_i18n.md":"ed2c8dd6","base_es6_let_const.md":"1a84e9b7","rsource_react_jsx.md":"42f8fd90","base_es6_proxy_reflect.md":"cc8da27d","base_javascript_scope.md":"f4a1ea42","rsource_react_functioncomponent.md":"77a4c2d6","node_base_fs.md":"08c946c2","rsource_react_multinode-dom-diff.md":"7d6a221f","work_utility_ni.md":"4ed797bc","work_git_method.md":"116e9433","work_git_principle.md":"875daf95","work_standard_project.md":"c20153cb","work_library_tailwind.md":"e2f64be9","work_question_npm.md":"05e4d708","rsource_react_lane.md":"450b5eb8","base_es6_extension.md":"8fc58153","rsource_react_event.md":"edce9ccc","frame_react_base_control.md":"0a1bd6d3","rsource_react_usememo_usecallback.md":"0d9b1c4f","base_structure_linklist.md":"4064eefd","rsource_react_useref.md":"fdae0ddf","vsource_vue_effect.md":"1d7afacf","work_git_command.md":"796f333a","node_norm_commonjs.md":"464757ad","rsource_react_usestate.md":"d7266184","work_command_command.md":"fc26d3af","wx_mini_optimize.md":"b8867908","node_nest_base.md":"af915d5d","rsource_react_updatequeue.md":"074172db","work_utility_vscode.md":"1df67a91","work_utility_picgo.md":"eb4d9b71","work_question_work.md":"63ae7703","rsource_react_singlenode-dom-diff.md":"2c86455c","work_utility_zsh.md":"c0226f8e","frame_react_base_virtualdom.md":"2a194430","frame_react_base_dataflow.md":"ddf45e48","rsource_react_schedule.md":"cfae841e","rsource_react_useeffect.md":"360b8e81","work_utility_nvm.md":"f1ee5dcc","base_typescript_interface.md":"d753d45b","node_base_stream.md":"929433a6","frame_react_base_jsx.md":"ab433f34","work_standard_git.md":"30276d80","node_base_global.md":"6395c994","work_utils_regexp.md":"fbbba7d1","work_standard_name.md":"c3d0bb9c","rsource_react_preknowledge.md":"f01ccb1c","rsource_react_uselayouteffect.md":"d8c75725","wx_qw_side.md":"7f8a78b4","node_npm_npm.md":"fa90c150","node_npm_pnpm.md":"016faac2","rsource_react_usereducer.md":"aa6e92e9","node_base_http.md":"5b3d97cb","frame_react_base_hoc.md":"c61a983f","rsource_react_scheduleupdateonfiber.md":"2bdc4c8b","base_es6_promise_promise.md":"04b43c99","frame_react-native_project.md":"587969c2","rsource_react_beginwork.md":"05e476d4","work_standard_code.md":"b191a671"}
